equit_ease/__init__.py
equit_ease/main.py
equit_ease/datatypes/__init__.py
equit_ease/datatypes/equity_meta.py
equit_ease/displayer/__init__.py
equit_ease/displayer/display.py
equit_ease/displayer/format.py
equit_ease/parser/__init__.py
equit_ease/parser/parse.py
equit_ease/reader/__init__.py
equit_ease/reader/read.py
equit_ease/utils/Colors.py
equit_ease/utils/Constants.py
equit_ease/utils/__init__.py
equit_ease/utils/decorators.py
tests/__init__.py
tests/test_chart_parser.py
tests/test_displayer.py
tests/test_parser.py
tests/test_quote_displayer.py
tests/test_quote_parser.py
tests/test_reader.py
tests/test_trends_displayer.py
tests/test_user_config_parser.py
EquitEase-0.0.8.dist-info/LICENSE
EquitEase-0.0.8.dist-info/METADATA
EquitEase-0.0.8.dist-info/WHEEL
EquitEase-0.0.8.dist-info/entry_points.txt
EquitEase-0.0.8.dist-info/top_level.txt
EquitEase-0.0.8.dist-info/RECORD
