Metadata-Version: 2.1
Name: EquitEase
Version: 0.0.8
Summary: The easiest way to retrieve equity data from the command line. Search Stocks, Options, Cryptocurrencies and other digital assets, and more in a manner of seconds.
Home-page: https://github.com/danmurphy1217/equit-ease
Author: Dan Murphy
Author-email: danielmurph8@gmail.com
License: UNKNOWN
Platform: UNKNOWN
Classifier: Programming Language :: Python :: 3
Classifier: License :: OSI Approved :: MIT License
Classifier: Operating System :: OS Independent
Requires-Python: >= 3.7
Requires-Dist: PyInquirer (==1.0.3)
Requires-Dist: requests (==2.25.1)
